klangooclient/MagnetAPIClient.py
klangooclient/MagnetAPIClientV2.py
klangooclient/__init__.py
klangooclient-1.0.0.dist-info/METADATA
klangooclient-1.0.0.dist-info/RECORD
klangooclient-1.0.0.dist-info/WHEEL
klangooclient-1.0.0.dist-info/top_level.txt
